gpst/__init__.py
gpst/__main__.py
gpst/data/__init__.py
gpst/data/load_track.py
gpst/data/save_track.py
gpst/data/track.py
gpst/data/processors/__init__.py
gpst/data/processors/calculator.py
gpst/data/processors/fix_elevation.py
gpst/data/reader/__init__.py
gpst/data/reader/fit_reader.py
gpst/data/reader/gpx_reader.py
gpst/data/reader/reader.py
gpst/data/writer/__init__.py
gpst/data/writer/gpx_writer.py
gpst/data/writer/writer.py
gpst/tools/__init__.py
gpst/tools/_common.py
gpst/tools/_tool_descriptor.py
gpst/tools/map.py
gpst/tools/plot.py
gpst/tools/process.py
gpst/utils/helpers.py
gpst/utils/logger.py
gpst-0.6.1.dist-info/licenses/LICENSE
gpst-0.6.1.dist-info/METADATA
gpst-0.6.1.dist-info/WHEEL
gpst-0.6.1.dist-info/entry_points.txt
gpst-0.6.1.dist-info/top_level.txt
gpst-0.6.1.dist-info/RECORD
